pdoc3k/__init__.py
pdoc3k/__main__.py
pdoc3k/cls.py
pdoc3k/consts.py
pdoc3k/doc.py
pdoc3k/error.py
pdoc3k/ext.py
pdoc3k/func.py
pdoc3k/module.py
pdoc3k/util.py
pdoc3k/var.py
pdoc3k/version.txt
pdoc3k/templates/LICENSE
pdoc3k/templates/README.md
pdoc3k/templates/__init__.py
pdoc3k/templates/html.mako
pdoc3k/templates/main.css
pdoc3k/templates/main.jinja2
pdoc3k/templates/normalize.css
pdoc3k/templates/print.css
pdoc3k/templates/toggle.js
pdoc3k/templates/util.jinja2
pdoc3k-0.0.0rc0.dist-info/LICENSE
pdoc3k-0.0.0rc0.dist-info/METADATA
pdoc3k-0.0.0rc0.dist-info/WHEEL
pdoc3k-0.0.0rc0.dist-info/entry_points.txt
pdoc3k-0.0.0rc0.dist-info/top_level.txt
pdoc3k-0.0.0rc0.dist-info/RECORD
