Metadata-Version: 2.1
Name: pdoc3k
Version: 0.0.0rc0
Summary: Placeholder
Home-page: https://example.com
Author: Mick Koch
Author-email: pypi@kochm.co
License: MIT
Project-URL: Documentation, https://example.com/docs
Platform: UNKNOWN
Classifier: Topic :: Documentation
Classifier: Topic :: Software Development :: Documentation
Classifier: Topic :: Utilities
Classifier: License :: OSI Approved :: MIT License
Classifier: Development Status :: 3 - Alpha
Classifier: Environment :: Console
Classifier: Intended Audience :: Developers
Classifier: Operating System :: OS Independent
Classifier: Programming Language :: Python :: 3
Classifier: Programming Language :: Python :: 3 :: Only
Requires-Python: ~=3.5
Requires-Dist: importlib-resources (~=1.0)
Requires-Dist: logbook (~=1.3)
Requires-Dist: mako (~=1.0)
Requires-Dist: markdown (~=2.6)
Provides-Extra: syntax_highlighting
Requires-Dist: pygments (~=2.4) ; extra == 'syntax_highlighting'
